<?xml version = '1.0' encoding = 'UTF-8'?>
<FKIndexAssociation class="oracle.dbtools.crest.model.design.relational.FKIndexAssociation" directorySegmentName="seg_0" id="ED7A420D-C98C-7DDA-BBDD-F48C2F8BCFA8" containerWithKeyObject="0758EA42-4027-99DA-CE58-59C9CC4A0C68" localFKIndex="C3030268-2EB5-6BC5-D601-5BA0FEB19C6A" name="branch_opn_cls_Brnch_inf_FK">
<createdBy>Admin</createdBy>
<createdTime>2023-01-09 12:52:01 UTC</createdTime>
<ownerDesignName>bankerd v9</ownerDesignName>
<referredTableLongName>Branch_info</referredTableLongName>
<deleteRule>NO ACTION</deleteRule>
<referredTableID>82297E2C-2530-6F24-6327-892F3330678B</referredTableID>
<keyObject>AAF1531D-0262-5ECC-C33F-C5EB786B7391</keyObject>
<referredKeyID>AAF1531D-0262-5ECC-C33F-C5EB786B7391</referredKeyID>
<mandatory>true</mandatory>
<refColNames>branch_code</refColNames>
<transferable>true</transferable>
<rely>false</rely>
<columnDependencyConstraintGenerateInDDL>true</columnDependencyConstraintGenerateInDDL>
</FKIndexAssociation>
